README.md
setup.py
stools/__init__.py
stools/utils.py
stools/version.py
stools.egg-info/PKG-INFO
stools.egg-info/SOURCES.txt
stools.egg-info/dependency_links.txt
stools.egg-info/entry_points.txt
stools.egg-info/not-zip-safe
stools.egg-info/requires.txt
stools.egg-info/top_level.txt
stools/clair/__init__.py
stools/clair/__main__.py
stools/clair/api.py
stools/clair/image.py
stools/clair/server/__init__.py
stools/clair/server/main.py
stools/clair/server/routes.py
stools/clair/server/views.py